gdbt/__init__.py
gdbt/cli.py
gdbt/code/__init__.py
gdbt/code/configuration.py
gdbt/code/templates.py
gdbt/dynamic/__init__.py
gdbt/dynamic/evaluation.py
gdbt/dynamic/lookup.py
gdbt/errors/__init__.py
gdbt/provider/__init__.py
gdbt/provider/grafana.py
gdbt/provider/prometheus.py
gdbt/provider/provider.py
gdbt/provider/s3.py
gdbt/resource/__init__.py
gdbt/resource/resource.py
gdbt/state/__init__.py
gdbt/state/plan.py
gdbt/state/state.py
gdbt-2.2.1.dist-info/entry_points.txt
gdbt-2.2.1.dist-info/LICENSE
gdbt-2.2.1.dist-info/WHEEL
gdbt-2.2.1.dist-info/METADATA
gdbt-2.2.1.dist-info/RECORD
