Metadata-Version: 2.1
Name: gdbt
Version: 2.2.1
Summary: Use Infrastructure as Code to provision and manage Grafana Dashboards from Templates
License: MIT
Author: Dmitry Kovalenko
Author-email: dmytro.kovalenko@ironsrc.com
Requires-Python: >=3.9,<4.0
Classifier: License :: OSI Approved :: MIT License
Classifier: Programming Language :: Python :: 3
Requires-Dist: Jinja2 (>=2.11.2,<3.0.0)
Requires-Dist: attrs (>=20.3.0,<21.0.0)
Requires-Dist: backoff (>=1.10.0,<2.0.0)
Requires-Dist: class-registry (>=2.1.2,<3.0.0)
Requires-Dist: click (>=7.1.2,<8.0.0)
Requires-Dist: deserialize (>=1.8.0,<2.0.0)
Requires-Dist: dictdiffer (>=0.8.1,<0.9.0)
Requires-Dist: dpath (>=2.0.1,<3.0.0)
Requires-Dist: envtoml (>=0.1.2,<0.2.0)
Requires-Dist: flatten-dict (>=0.3.0,<0.4.0)
Requires-Dist: grafana-api (>=1.0.3,<2.0.0)
Requires-Dist: halo (>=0.0.31,<0.0.32)
Requires-Dist: jsonpath-ng (>=1.5.2,<2.0.0)
Requires-Dist: python-configuration[toml,yaml] (>=0.8.1,<0.9.0)
Requires-Dist: python-consul2 (>=0.1.5,<0.2.0)
Requires-Dist: requests (>=2.25.0,<3.0.0)
Requires-Dist: rich (>=10.2.1,<11.0.0)
Requires-Dist: s3path (>=0.2.205,<0.3.0)
Requires-Dist: semver (>=2.13.0,<3.0.0)
